<?xml version="1.0" encoding="utf-8"?>
<LanguageData>

  <!-- 여물 작성 -->

  <MakeR_Manger10.label>여물(10)</MakeR_Manger10.label>
  <MakeR_Manger10.description>짚과 쌀겨、곡물을 합쳐서 돌물의 사료(고영양소)를 만든다.</MakeR_Manger10.description>
  <MakeR_Manger10.jobString>여물을 만든다</MakeR_Manger10.jobString>

  <MakeR_Manger50.label>여물(50)</MakeR_Manger50.label>
  <MakeR_Manger50.description>짚과 쌀겨、곡물을 합쳐서 돌물의 사료(고영양소)를 만든다.</MakeR_Manger50.description>
  <MakeR_Manger50.jobString>여물을 만든다</MakeR_Manger50.jobString>

  <MakeR_Manger100.label>여물(100)</MakeR_Manger100.label>
  <MakeR_Manger100.description>짚과 쌀겨、곡물을 합쳐서 돌물의 사료(고영양소)를 만든다.</MakeR_Manger100.description>
  <MakeR_Manger100.jobString>여물을 만든다</MakeR_Manger100.jobString>


</LanguageData>